agentcraft_mcp/__init__.py
agentcraft_mcp/agent_manager.py
agentcraft_mcp/config.py
agentcraft_mcp/data_processor.py
agentcraft_mcp/http_client.py
agentcraft_mcp/server.py
agentcraft_mcp/tools.py
agentcraft_mcp-0.1.0.dist-info/METADATA
agentcraft_mcp-0.1.0.dist-info/WHEEL
agentcraft_mcp-0.1.0.dist-info/top_level.txt
agentcraft_mcp-0.1.0.dist-info/RECORD
