Metadata-Version: 2.2
Name: agentcraft_mcp
Version: 0.1.0
Summary: AgentCraft MCP Server: A secure and scalable AI agent framework
Home-page: https://github.com/seyhunak/agentcraft
Author: Seyhun Akyurek
Author-email: seyhunak@gmail.com
Requires-Python: >=3.7
Requires-Dist: uvicorn>=0.34.0
Requires-Dist: python-dotenv
Requires-Dist: mcp
Requires-Dist: spacy
Requires-Dist: spacy-transformers
Requires-Dist: pyyaml
Requires-Dist: aiohttp
Dynamic: author
Dynamic: author-email
Dynamic: home-page
Dynamic: requires-python
